DataMemory(RAM).v
`timescale 1ns / 1ps
//////////////////////////////////////////////////////////////////////////////////
// Company: 
// Engineer: 
// 
// Create Date:    16:21:04 10/10/2017 
// Design Name: 
// Module Name:    DM 
// Project Name: 
// Target Devices: 
// Tool versions: 
// Description: 
//
// Dependencies: 
//
// Revision: 
// Revision 0.01 - File Created
// Additional Comments: 
//
//////////////////////////////////////////////////////////////////////////////////
//This is the 128 bytes memory  to store data and read data for loading onto registers
module DataMemory(input wire			clk,
		input wire	[6:0]	addr,
		input wire rd, wr,
		input wire 	[7:0]	wdata,
		output reg [7:0]	rdata);

	parameter mem_size = 128, width = 8;	//128 bytes memory each of 8 bit width
	reg [width-1:0] mem [0:mem_size-1];  

	always @(posedge clk) begin				//write or Read happens positive edge of clk
		if (wr) begin
			mem[addr] <= wdata;				
		end
	end
	// During a write, avoid the one cycle delay by reading from 'wdata'
	always @* begin
		if(rd) begin
			rdata <= mem[addr];
		end	
	end			
	
endmodule

ALU.v
`timescale 1ns / 1ps
//////////////////////////////////////////////////////////////////////////////////
// Company: 
// Engineer: 
// 
// Create Date:    16:24:52 10/10/2017 
// Design Name: 
// Module Name:    ALU 
// Project Name: 
// Target Devices: 
// Tool versions: 
// Description: 
//
// Dependencies: 
//
// Revision: 
// Revision 0.01 - File Created
// Additional Comments: 
//
//////////////////////////////////////////////////////////////////////////////////
module ALU(input enable,input [3:0]	fn_sel,
		input	 [7:0]	a, b,
		output reg	[7:0]	out,
		input cmpflag);				

	//All alu operations have 3 operands , 1st destination, 2nd input1, 3rd input2.
	//except Dec and Inc where only one operand used.

	parameter z=3'd0,c=3'd1,v=3'd2,s=3'd3; 
	//z is zero flag, c is carry flag,v is overflow,s is signed bit flag
	//Parameters are just used for more readablitiy.

	wire [8:0] sub_ab;			//subtraction
	wire [8:0] add_ab;			//Addition		
	wire [8:0] left_shift_ab;	//LeftShift
	wire [8:0] right_shift_ab;	//RightShift
	wire [8:0]	decrement_a, increment_a; //Decrement and Increment

	reg [3:0]flags;				//Status Register or Flags

	assign add_ab = a+b;			//Add operation	
	assign sub_ab = a-b;			//Sub operation
	assign left_shift_ab = a<<b;	//leftshift a by b units
	assign right_shift_ab = a>>b;	//right shift a by b units
	assign decrement_a = a-1;		//Dec a by 1
	assign increment_a = a+1;		// Inc a by 1
		
	always @(posedge enable) begin
		case (fn_sel)				
			4'd0:  								//Add
			begin
				out <= add_ab;
				if(add_ab[8]==1'd1)begin		//When the 9th bit of output is 1 then it has carry or overflow 
					flags[c] = 1'd1;
					flags[v] = 1'd1;
				end	
				else begin
					flags[c] = 1'd0;
					flags[v] = 1'd0;
				end
			end
			4'd1: 								//Subtract			
			begin
				out <= sub_ab;
				if(sub_ab[8]==1'd1)begin		//9th bit is 1 when output is 2's compliment of negative number 
					flags[s] = 1'd1;			//obtained by subtracting
					flags[v] = 1'd1;
				end		
				if(a<b)begin					//if a<b subtraction gives negative result
					flags[s] = 1'd1;
				end	
				else begin
					flags[s] = 1'd0;
					flags[v] = 1'd0;
				end	
			end
			4'd2:  out <= a & b;					//And operation
			4'd3:  out <= a | b;					//Or operation
			4'd4:  									//LEft shift
			begin
				out <= left_shift_ab;
				if(left_shift_ab[8]==1'd1)begin		//overflow when 9th bit is 1 while shifting
						flags[v] = 1'd1;
				end		
				else begin
					flags[v] = 1'd0;
				end	
			end				
			4'd5:  									//Right shift
			begin
				out <= right_shift_ab;
				if(right_shift_ab[8]==1'd1)begin	//overflow when 9th bit is 1 while shifting
						flags[v] = 1'd1;
				end		
				else begin
					flags[v] = 1'd0;
				end	
			end		
			4'd6:									//Decrement Register
			begin
				out <= decrement_a;
				if(decrement_a[8]==1'd1)begin	//9th bit is 1 when output is 2's compliment of negative number 
					flags[s] = 1'd1;			//obtained by decrementing
					flags[v] = 1'd1;
				end		
				else begin
					flags[s] = 1'd0;
					flags[v] = 1'd0;
				end	

			end		
			4'd7:									//Increment Register
			begin
				out <= increment_a;
				if(increment_a[8]==1'd1)begin		//overflow when 9th bit is 1 while incrementing
						flags[v] = 1'd1;
				end		
				else begin
					flags[v] = 1'd0;
				end	
			end	
			default: out <= 0;					
		endcase

		if(out==8'd0)begin							//when output is zero 
			flags[z] =1'd1;							//Zero flag is set
		end	
		else begin						
			flags[z] = cmpflag-1;					//or zero flag is set when CMP two equal numbers.
		end	
	end

endmodule

InternalMemory.v
`timescale 1ns / 1ps
//////////////////////////////////////////////////////////////////////////////////
// Company: 
// Engineer: 
// 
// Create Date:    14:41:07 10/17/2017 
// Design Name: 
// Module Name:    IM 
// Project Name: 
// Target Devices: 
// Tool versions: 
// Description: 
//
// Dependencies: 
//
// Revision: 
// Revision 0.01 - File Created
// Additional Comments: 
//
//////////////////////////////////////////////////////////////////////////////////
//This is internal registers module which contains 6 registers 
//used for writing and reading from the registers.
module InternalMemory(input wire [2:0] addr,
			input wire wr,rd,
			input  [7:0] in_data,
			output reg [7:0] out_data
    );
	// 6 registers each of 8bit.
	reg [7:0] r0,r1,r2,r3,r4,r5;

	always@*begin
		if(wr) begin				//writing into registers depending on the address given from CU_EU
			case(addr)
			3'b000: r0 <= in_data;
			3'b001: r1 <= in_data;
			3'b010: r2 <= in_data;
			3'b011: r3 <= in_data;
			3'b100: r4 <= in_data;
			3'b101: r5 <= in_data;
			endcase
		end
		else if(rd) begin			//Reading from registers depending on the address given from CU_EU
				case(addr)
				3'b000:  out_data <= r0;
				3'b001:  out_data <= r1;
				3'b010:  out_data <= r2;
				3'b011:  out_data <= r3;
				3'b100:  out_data <= r4;
				3'b101:  out_data <= r5;
				endcase
			end
	end
	
endmodule

ProgramMemory.v
`timescale 1ns / 1ps
//////////////////////////////////////////////////////////////////////////////////
// Company: 
// Engineer: 
// 
// Create Date:    15:05:20 10/31/2017 
// Design Name: 
// Module Name:    InstructionMEM 
// Project Name: 
// Target Devices: 
// Tool versions: 
// Description: 
//
// Dependencies: 
//
// Revision: 
// Revision 0.01 - File Created
// Additional Comments: 
//
//////////////////////////////////////////////////////////////////////////////////
module InstructionMemory (input wire	clk,
		input wire	[6:0]	addr,
		input wire	rd,
		output wire	[15:0]	rdata);

	//Maximum 128 lines of instructions with each 0f 16bits.
	//READ ONLY MEMORY
    parameter max_instruc = 128, width = 16;
	reg [width-1:0] mem [0:max_instruc-1];  

	//Instruction is of 16 bit wide.
	//LSB of instruction is used for stopping the program
	//so if LSB is 1 it is the last instruction.
	//so otherwise LSB should be zero.

	//writing instructions to memory through binary file created assembler.py by compiling programs
	always@(posedge clk)begin							
		$readmemb("instructions.dat", mem,0,12);	// 0-12 is the no of instructions of a program
	end												//should be changed manually

	// //1 . Program to find factorial of number n!
	// mem[7'd0] = 16'b1001000000000000; 	//Ldi r0,#0
	// mem[7'd1] = 16'b1001001000001100; 	//Ldi r1,#6
	// mem[7'd2] = 16'b1001010000000010; 	//Ldi r2,#1
	// mem[7'd3] = 16'b1100011001000000;   //Mov r3,r1  //opcode = 1100
	// mem[7'd4] = 16'b1100101001000000;   //Mov r5,r1  //opcode = 1100
	// // mem[7'd5] = 16'b0001001001010000;   //sub r5,r1,r2 	
	// mem[7'd5] = 16'b0001100001010000;   //sub r4,r1,r2 
	// mem[7'd6] = 16'b0000011011101000;   //Add r3,r3,r5 
	// mem[7'd7] = 16'b0001100100010000;   //sub r4,r4,r2 
	// mem[7'd8] = 16'b1101100000011000;   //CMP r4,r0       //OPcode = 1101	
	// mem[7'd9] = 16'b1110000110100000;   //BE #address(13) //OPcode = 1110
	// mem[7'd10] = 16'b1101100010011000;   //CMP r4,r2       //OPcode = 1101	
	// mem[7'd11] = 16'b1111000011100000;   //BNE #address(7) //OPcode = 1111
	// mem[7'd12] = 16'b1100101011110000;  //Mov r5,r3  //opcode = 1100
	// mem[7'd13] = 16'b0001001001010000;  //sub r1,r1,r2 
	// mem[7'd14] = 16'b1101001010011000;  //CMP r1,r2     //OPcode = 1101
	// mem[7'd15] = 16'b1111000011000000; 	//BNE #address(6) //OPcode = 1111
	// mem[7'd16] = 16'b1011101000000101;  //str r5,#01 

	// //2 . Program to store nth fibonacci number in the memory excluding 0 and 1.
	// mem[7'd0] = 16'b1001000000000000; 	//Ldi r0,#0
	// mem[7'd1] = 16'b1001001000000010; 	//Ldi r1,#1
	// mem[7'd2] = 16'b1001100000010000; 	//Ldi r4,#8
	// mem[7'd3] = 16'b1100011001000000;   //Mov r3,r1  //opcode = 1100
	// mem[7'd4] = 16'b1100010000000000;   //Mov r2,r0  //opcode = 1100
	// mem[7'd5] = 16'b0000101011000010;   //add r5,r3,r0 	
	// mem[7'd6] = 16'b0001100100001000;   //sub r4,r4,r1
	// mem[7'd7] = 16'b1100000011000000;   //Mov r0,r3  //opcode = 1100
	// mem[7'd8] = 16'b1100011101000000;   //Mov r3,r5  //opcode = 1100
	// mem[7'd9] = 16'b1101100010011000;   //CMP r4,r2       //OPcode = 1101
	// mem[7'd10] = 16'b1111000010100000; 	//BNE #address(5) //OPcode = 1111
	// mem[7'd11] = 16'b1011101000000100;  //str r5,#01 
	// mem[7'd12] = 16'b1010001000001001; 	//Ld r1,#01(mem_Address)
	
	// mem[7'd8] = 16'b1110000101000000;   //Branch #address(10) //Opcode = 1110 (Unconditional)
	// mem[7'd9] = 16'b0000001010011000;   //Add r1,r2,r3 
	// mem[7'd10] = 16'b1001011000000100; 	//Ldi r3,#2
	// mem[7'd14] = 16'b0001100010011000;   //sub r4,r2,r3 
	// mem[7'd15] = 16'b0000100100011001;   //Add r4,r4,r3 
	
		assign rdata = (rd)? mem[addr]: 1'd0;
endmodule

CU_EU.v
`timescale 1ns / 1ps
//////////////////////////////////////////////////////////////////////////////////
// Company: 
// Engineer: 
// 
// Create Date:    14:40:56 10/17/2017 
// Design Name: 
// Module Name:    CU 
// Project Name: 
// Target Devices: 
// Tool versions: 
// Description: 
//
// Dependencies: 
//
// Revision: 
// Revision 0.01 - File Created
// Additional Comments: 
//
//////////////////////////////////////////////////////////////////////////////////
module CU_EU(input wire clk, input wire enableCU);

	//control cum Execution unit
	
	output reg [6:0] pc;					//program counter [7 bit address]
	output reg Load,Store,Read,Write;		//status signals like read write load store
	parameter fetch = 0, decode = 1, fetch_operand = 2, execute = 3, store = 4;	//these are the states
	// totally 5 states, parameters are used for readability.

	reg [2:0]state;
	reg enable,Cmpflag;
	wire [15:0] instruction;
	reg [3:0] op_code;
	reg [2:0] Rdes,Ra,Rb,register_addr;
	reg [7:0] Direct_Input;
	wire [7:0] register_oper,oper3_w,oper1_w;
	reg [7:0] oper1,oper2,oper3,register_in;
	reg [6:0] src_addr,mem_address,des_addr;

	initial begin
		state = fetch;
		pc = 7'd0;
		Cmpflag = 1'd0;
		enable <= 1'd0;			//ALu is intially switched off
	end

	//Connecting CU_EU with program memory
	InstructionMemory instruc_mem(.clk(clk),
			.addr(pc),					//address of instruction
			.rd(1'd1),
			.rdata(instruction));		//output		

	//Connecting CU_EU with internal memory (6 Registers R0-R5)		
	InternalMemory internal_mem(.addr(register_addr),
					.wr(Write),
					.rd(Read),
					.in_data(register_in),
					.out_data(register_oper));

	always@*begin
		op_code <= instruction[15:12];
	end	

	//Connecting CU_EU with ALU
	ALU alu (
		.enable(enable),
		.fn_sel(op_code), 
		.a(oper1), 
		.b(oper2),
		.out(oper3_w), 
		.cmpflag(Cmpflag)
	);

	DataMemory data_mem(.clk(clk),
				.addr(mem_address),
				.rd(Read),
				.wr(Write),
				.wdata(oper1),
				.rdata(oper1_w));

	always@(posedge (clk*enableCU))begin
		case(state)
		fetch:
			begin
				Read = 1'd1;
				Write = 1'd0;
				Load = 1'd0;
				Store = 1'd0;
				state <= state+1;
				
			end	
		decode:
			begin
				op_code <= instruction[15:12];
				if(op_code[3]==1'd0)begin
					//Alu operation
					if(op_code[3:1]!=3'b011)begin
						Rdes <= instruction[11:9];
						Ra <= instruction[8:6];
						Rb <= instruction[5:3];
					end
					else begin
						Ra <= instruction[11:9];
					end		
				end
				else if(op_code[3:1]==3'b110)begin
					//Mov and CMP
					Load <= 1'd0;
					Read <= 1'd1;
					Write <= 1'd0;
					Store <= 1'd0;
					//ra <- rb and ra-rb
					Ra <= instruction[11:9];
					Rb <= instruction[8:6];				
				end
				else if(op_code==4'b1001)begin
					//LoadImediate
					//ra <- #number
					Ra <= instruction[11:9];
					Direct_Input <= instruction[8:1];			

				end
				else if(op_code==4'b1010)begin
					//Load
					//ra <- #mem_address
					Ra <= instruction[11:9];
					src_addr <= instruction[8:2];
				end
				else if(op_code==4'b1011)begin
					//Store
					Ra <= instruction[11:9];
					des_addr <= instruction[8:2];
				end
				else if(op_code[3:1]==3'b111)begin
					//BE and BNE
					des_addr <= instruction[11:5];
					state <= execute;
				end	
				if(op_code[3:1]!=3'b111)begin
					state <= state+1;
				end
			end
		fetch_operand:
			begin
				Read <= 1'd1;
				Write <= 1'd0;
				Load <= 1'd0;
				Store <= 1'd0;
	 			if(op_code[3]==1'd0)begin
				 //ALU
				 	if(op_code[3:1]!=3'b011)begin
						register_addr <= Rdes;
						#1oper3 <= register_oper;
						register_addr <= Ra;
						#1oper1 <= register_oper;
						register_addr <= Rb;
						#1oper2 <= register_oper;
					end
					else begin
						register_addr <= Ra;
						#1oper1 <= register_oper;
					end	
				end
				else if(op_code[3:1]==3'b110)begin
					//Mov or CMP
					//ra <- rb or ra-rb
					register_addr <= Ra;
					#1oper1 <= register_oper;
					register_addr <= Rb;
					#1oper2 <= register_oper;
				end
				else begin
					//Load,LDI,Store
					register_addr <= Ra;
					oper1 <= register_oper;
				end
				state <= state+1;		
			end
		execute:
			begin
				if(op_code[3]==1'd0)begin
					enable <= 1'd1;	
					if(op_code[3:1]!=3'b011)begin			//ALU is now turned ON
						oper3 <= oper3_w;
					end
					else begin
						oper1 <= oper3_w;					//For Dec and Inc 
					end		
				end
				else if(op_code==4'b1001)begin
					//LoadImediate
					//ra <- #number
					enable <= 1'd0;
					Write <= 1'd0;
					Read <= 1'd1;
					Store <= 1'd0;
					Load <= 1'd1;

					oper1 <= Direct_Input;
				end
				else if(op_code==4'b1010)begin
					//Load
					//ra <- #memaddress
					enable <= 1'd0;					
					Write <= 1'd0;
					Read <= 1'd1;
					Store <= 1'd0;
					Load <= 1'd1;
					mem_address <= src_addr;
					
				end
				else if(op_code==4'b1011)begin
					//Store
					Write <= 1'd1;
					Read <= 1'd0;
					Store <= 1'd1;
					Load <= 1'd0;
					enable <= 1'd0;					
					mem_address <= des_addr;

				end
				else if(op_code==4'b1100)begin
					//Mov
					//ra <- rb
					oper1 <=  oper2;
					enable <= 1'd0;
					
				end
				else if(op_code==4'b1101)begin
					//CMP
					//ra-rb
					enable <= 1'd0;
					
					if(oper1 == oper2)begin
						Cmpflag <= 1'd0;
					end
					else begin
						Cmpflag <= 1'd1;
					end		
					
				end
				else if(op_code==4'b1110)begin
					//BranchifEqual
					Write <= 1'd0;
					Read <= 1'd0;
					Store <= 1'd0;
					Load <= 1'd0;
					enable <= 1'd0;

					if(Cmpflag == 1'd0)begin
						pc <= des_addr;
						state <= fetch;
					end	
					else begin
						pc <= pc+1;
						state <= fetch;
					end	
			
				end	
				else if(op_code==4'b1111)begin
					//BNE
					Write <= 1'd0;
					Read <= 1'd0;
					Store <= 1'd0;
					enable <= 1'd0;
					Load <= 1'd0;
					if(Cmpflag == 1'd1)begin
						pc <= des_addr;
						state <= fetch;
					end	
					else begin
						pc <= pc+1;
						state <= fetch;
					end	
				end	
				
				if(op_code[3:1]!=3'b111)begin
					state <= state+1;
				end
		end
		store:
			begin
				if(op_code[3]==1'd0)begin
					//ALU
					enable <= 1'd0;
					Write <= 1'd1;
					Read <= 1'd0;
					Store <= 1'd0;
					Load <= 1'd0;
					if(op_code[3:1]!=3'b011)begin
						register_addr <= Rdes;
						register_in <= oper3_w;
					end
					else begin
						register_addr <= Ra;
						register_in <= oper3_w;
					end		

				end
				else if(op_code==4'b1100)begin
					//Mov
					//ra <- rb
					Write <= 1'd1;
					Read <= 1'd0;
					Store <= 1'd0;
					Load <= 1'd0;
					register_addr <= Ra;
					register_in <= oper1;

				end
				else if(op_code==4'b1001)begin
					//LoadImediate
					//ra <- #number
					Write <= 1'd1;
					Read <= 1'd0;
					Store <= 1'd0;
					Load <= 1'd1;
					register_addr <= Ra;
					register_in <= oper1;
				end
				else if(op_code==4'b1010)begin
					//Load
					//ra <- #memaddress
					Write <= 1'd1;
					Read <= 1'd0;
					Store <= 1'd0;
					Load <= 1'd1;
					register_addr <= Ra;
					register_in <= oper1;					
				end

				if(instruction[0]==1'd0)begin
					pc <= pc+1;
					state <= fetch;
				end
				
			end
		endcase
	end		 
		
endmodule

cputb.v
`timescale 1ns / 1ps
module cpu_test;
//This is the test bench for this whole processor
reg clk;
wire enableCU;

assign enableCU = 1'd1;             //To switch on the CPU
//Control cum Execution unit instantiation.
CU_EU cu_eu_UnitTest(.clk(clk),
                  .enableCU(enableCU));  

initial
    begin
    $dumpfile("cpu_wave.vcd");          //dumpfile is created for simulating in GTKWAVE
    $dumpvars(0,cpu_test);              //simulation have topmodule, so basically everything can be
                                        //viewed in it
    clk = 0;                            //clk generation
    repeat(1000)#10 clk =~clk;          
end

endmodule

cpu_wave.vcd
$date
	Tue Nov  7 15:43:12 2017
$end
$version
	Icarus Verilog
$end
$timescale
	1ps
$end
$scope module cpu_test $end
$var wire 1 ! enableCU $end
$var reg 1 " clk $end
$scope module cu_eu_UnitTest $end
$var wire 1 # clk $end
$var wire 1 ! enableCU $end
$var wire 16 $ instruction [15:0] $end
$var wire 8 % oper1_w [7:0] $end
$var wire 8 & oper3_w [7:0] $end
$var wire 8 ' register_oper [7:0] $end
$var reg 1 ( Cmpflag $end
$var reg 8 ) Direct_Input [7:0] $end
$var reg 1 * Load $end
$var reg 3 + Ra [2:0] $end
$var reg 3 , Rb [2:0] $end
$var reg 3 - Rdes [2:0] $end
$var reg 1 . Read $end
$var reg 1 / Store $end
$var reg 1 0 Write $end
$var reg 7 1 des_addr [6:0] $end
$var reg 1 2 enable $end
$var reg 7 3 mem_address [6:0] $end
$var reg 4 4 op_code [3:0] $end
$var reg 8 5 oper1 [7:0] $end
$var reg 8 6 oper2 [7:0] $end
$var reg 8 7 oper3 [7:0] $end
$var reg 7 8 pc [6:0] $end
$var reg 3 9 register_addr [2:0] $end
$var reg 8 : register_in [7:0] $end
$var reg 7 ; src_addr [6:0] $end
$var reg 3 < state [2:0] $end
$scope module instruc_mem $end
$var wire 7 = addr [6:0] $end
$var wire 1 # clk $end
$var wire 1 > rd $end
$var wire 16 ? rdata [15:0] $end
$upscope $end
$scope module internal_mem $end
$var wire 3 @ addr [2:0] $end
$var wire 8 A in_data [7:0] $end
$var wire 1 B rd $end
$var wire 1 C wr $end
$var reg 8 D out_data [7:0] $end
$var reg 8 E r0 [7:0] $end
$var reg 8 F r1 [7:0] $end
$var reg 8 G r2 [7:0] $end
$var reg 8 H r3 [7:0] $end
$var reg 8 I r4 [7:0] $end
$var reg 8 J r5 [7:0] $end
$upscope $end
$scope module alu $end
$var wire 8 K a [7:0] $end
$var wire 9 L add_ab [8:0] $end
$var wire 8 M b [7:0] $end
$var wire 1 N cmpflag $end
$var wire 9 O decrement_a [8:0] $end
$var wire 1 P enable $end
$var wire 4 Q fn_sel [3:0] $end
$var wire 9 R increment_a [8:0] $end
$var wire 9 S left_shift_ab [8:0] $end
$var wire 9 T right_shift_ab [8:0] $end
$var wire 9 U sub_ab [8:0] $end
$var reg 4 V flags [3:0] $end
$var reg 8 W out [7:0] $end
$upscope $end
$scope module data_mem $end
$var wire 7 X addr [6:0] $end
$var wire 1 # clk $end
$var wire 1 B rd $end
$var wire 8 Y wdata [7:0] $end
$var wire 1 C wr $end
$var reg 8 Z rdata [7:0] $end
$upscope $end
$upscope $end
$upscope $end
$enddefinitions $end
#0
$dumpvars
bx Z
bx Y
bx X
bx W
bx V
bx U
bx T
bx S
bx R
bx Q
0P
bx O
0N
bx M
bx L
bx K
bx J
bx I
bx H
bx G
bx F
bx E
bx D
xC
xB
bx A
bx @
bx ?
1>
b0 =
b0 <
bx ;
bx :
bx 9
b0 8
bx 7
bx 6
bx 5
bx 4
bx 3
02
bx 1
x0
x/
x.
bx -
bx ,
bx +
x*
bx )
0(
bx '
bx &
bx %
bx $
0#
0"
1!
$end
#10000
b1001 4
b1001 Q
b1 <
b1001000000000000 $
b1001000000000000 ?
0/
0*
00
0C
1.
1B
1"
1#
#20000
0"
0#
#30000
b10 <
b0 )
b0 +
1"
1#
#40000
0"
0#
#50000
b11 <
b0 9
b0 @
1"
1#
#60000
0"
0#
#70000
b111111111 O
b1 R
b100 <
b0 5
b0 K
b0 Y
1*
1"
1#
#80000
0"
0#
#90000
b0 E
b0 <
b1 8
b1 =
b1001001000000010 $
b1001001000000010 ?
b0 :
b0 A
0.
0B
10
1C
1"
1#
#100000
0"
0#
#110000
b0 D
b0 '
b1 <
0*
00
0C
1.
1B
1"
1#
#120000
0"
0#
#130000
b10 <
b1 )
b1 +
1"
1#
#140000
0"
0#
#150000
bx D
bx '
b11 <
b1 9
b1 @
1"
1#
#160000
0"
0#
#170000
b0 O
b10 R
b100 <
b1 5
b1 K
b1 Y
1*
1"
1#
#180000
0"
0#
#190000
b1 F
b0 <
b10 8
b10 =
b1001100000010000 $
b1001100000010000 ?
b1 :
b1 A
0.
0B
10
1C
1"
1#
#200000
0"
0#
#210000
b1 D
b1 '
b1 <
0*
00
0C
1.
1B
1"
1#
#220000
0"
0#
#230000
b10 <
b1000 )
b100 +
1"
1#
#240000
0"
0#
#250000
bx D
bx '
b11 <
b100 9
b100 @
1"
1#
#260000
0"
0#
#270000
b111 O
b1001 R
b100 <
b1000 5
b1000 K
b1000 Y
1*
1"
1#
#280000
0"
0#
#290000
b1100 4
b1100 Q
b1000 I
b0 <
b11 8
b11 =
b1100011001000000 $
b1100011001000000 ?
b1000 :
b1000 A
0.
0B
10
1C
1"
1#
#300000
0"
0#
#310000
b1000 D
b1000 '
b1 <
0*
00
0C
1.
1B
1"
1#
#320000
0"
0#
#330000
b10 <
b1 ,
b11 +
1"
1#
#340000
0"
0#
#350000
bx D
bx '
b11 9
b11 @
1"
1#
#351000
b1 D
b1 '
bx O
bx R
b1 9
b1 @
bx 5
bx K
bx Y
#352000
b11 <
b1 6
b1 M
bx0 S
b0xxxxxxx T
#360000
0"
0#
#370000
b0 O
b10 R
b100 <
b1 5
b1 K
b1 Y
b10 L
b0 U
b10 S
b0 T
1"
1#
#380000
0"
0#
#390000
b1 H
b0 <
b100 8
b100 =
b1100010000000000 $
b1100010000000000 ?
b1 :
b1 A
b11 9
b11 @
0.
0B
10
1C
1"
1#
#400000
0"
0#
#410000
b1 <
00
0C
1.
1B
1"
1#
#420000
0"
0#
#430000
b10 <
b0 ,
b10 +
1"
1#
#440000
0"
0#
#450000
bx D
bx '
b10 9
b10 @
1"
1#
#451000
b0 D
b0 '
bx O
bx R
b0 9
b0 @
bx 5
bx K
bx Y
bx L
bx U
bx0 S
b0xxxxxxx T
#452000
b11 <
b0 6
b0 M
b0xxxxxxxx S
b0xxxxxxxx T
#460000
0"
0#
#470000
b111111111 O
b1 R
b100 <
b0 5
b0 K
b0 Y
b0 L
b0 U
b0 S
b0 T
1"
1#
#480000
0"
0#
#490000
b0 4
b0 Q
b0 G
b0 <
b101 8
b101 =
b101011000000 $
b101011000000 ?
b0 :
b0 A
b10 9
b10 @
0.
0B
10
1C
1"
1#
#500000
0"
0#
#510000
b1 <
00
0C
1.
1B
1"
1#
#520000
0"
0#
#530000
b10 <
b11 +
b101 -
1"
1#
#540000
0"
0#
#550000
bx D
bx '
b101 9
b101 @
1"
1#
#551000
b1 D
b1 '
b11 9
b11 @
#552000
b0 D
b0 '
b0 O
b10 R
b0 9
b0 @
b1 5
b1 K
b1 Y
b1 L
b1 U
b1 S
b1 T
#553000
b11 <
#560000
0"
0#
#570000
b1 W
b1 &
bx001 V
b100 <
12
1P
1"
1#
#580000
0"
0#
#590000
b110 4
b110 Q
b1 J
b0 <
b110 8
b110 =
b110100000000000 $
b110100000000000 ?
b1 :
b1 A
b101 9
b101 @
0.
0B
10
1C
02
0P
1"
1#
#600000
0"
0#
#610000
b1 D
b1 '
b1 <
00
0C
1.
1B
1"
1#
#620000
0"
0#
#630000
b10 <
b100 +
1"
1#
#640000
0"
0#
#650000
b1000 D
b1000 '
b100 9
b100 @
1"
1#
#651000
b111 O
b1001 R
b11 <
b1000 5
b1000 K
b1000 Y
b1000 L
b1000 U
b1000 S
b1000 T
#660000
0"
0#
#670000
b111 W
b111 &
b0 O
b10 R
b1 V
b100 <
b1 5
b1 K
b1 Y
b1 L
b1 U
b1 S
b1 T
12
1P
1"
1#
#680000
0"
0#
#690000
b1100 4
b1100 Q
b111 I
b0 <
b111 8
b111 =
b1100000011000000 $
b1100000011000000 ?
b111 :
b111 A
0.
0B
10
1C
02
0P
1"
1#
#700000
0"
0#
#710000
b111 D
b111 '
b1 <
00
0C
1.
1B
1"
1#
#720000
0"
0#
#730000
b10 <
b11 ,
b0 +
1"
1#
#740000
0"
0#
#750000
b0 D
b0 '
b0 9
b0 @
1"
1#
#751000
b1 D
b1 '
b111111111 O
b1 R
b11 9
b11 @
b0 5
b0 K
b0 Y
b0 L
b0 U
b0 S
b0 T
#752000
b11 <
b1 6
b1 M
b1 L
b111111111 U
#760000
0"
0#
#770000
b0 O
b10 R
b100 <
b1 5
b1 K
b1 Y
b10 L
b0 U
b10 S
1"
1#
#780000
0"
0#
#790000
b1 E
b0 <
b1000 8
b1000 =
b1100011101000000 $
b1100011101000000 ?
b1 :
b1 A
b0 9
b0 @
0.
0B
10
1C
1"
1#
#800000
0"
0#
#810000
b1 <
00
0C
1.
1B
1"
1#
#820000
0"
0#
#830000
b10 <
b101 ,
b11 +
1"
1#
#840000
0"
0#
#850000
b11 9
b11 @
1"
1#
#851000
b101 9
b101 @
#852000
b11 <
#860000
0"
0#
#870000
b100 <
1"
1#
#880000
0"
0#
#890000
b1101 4
b1101 Q
b0 <
b1001 8
b1001 =
b1101100010000000 $
b1101100010000000 ?
b11 9
b11 @
0.
0B
10
1C
1"
1#
#900000
0"
0#
#910000
b1 <
00
0C
1.
1B
1"
1#
#920000
0"
0#
#930000
b10 <
b10 ,
b100 +
1"
1#
#940000
0"
0#
#950000
b111 D
b111 '
b100 9
b100 @
1"
1#
#951000
b0 D
b0 '
b110 O
b1000 R
b10 9
b10 @
b111 5
b111 K
b111 Y
b1000 L
b110 U
b1110 S
b11 T
#952000
b11 <
b0 6
b0 M
b111 L
b111 U
b111 S
b111 T
#960000
0"
0#
#970000
b100 <
1(
1N
1"
1#
#980000
0"
0#
#990000
b1111 4
b1111 Q
b0 <
b1010 8
b1010 =
b1111000010100000 $
b1111000010100000 ?
1"
1#
#1000000
0"
0#
#1010000
b1 <
1"
1#
#1020000
0"
0#
#1030000
b11 <
b101 1
1"
1#
#1040000
0"
0#
#1050000
b0 4
b0 Q
b0 <
b101 8
b101 =
b101011000000 $
b101011000000 ?
0.
0B
1"
1#
#1060000
0"
0#
#1070000
b1 <
1.
1B
1"
1#
#1080000
0"
0#
#1090000
b10 <
b0 ,
b11 +
1"
1#
#1100000
0"
0#
#1110000
b1 D
b1 '
b101 9
b101 @
1"
1#
#1111000
b11 9
b11 @
b1 7
#1112000
b0 O
b10 R
b0 9
b0 @
b1 5
b1 K
b1 Y
b1 L
b1 U
b1 S
b1 T
#1113000
b11 <
b1 6
b1 M
b10 L
b0 U
b10 S
b0 T
#1120000
0"
0#
#1130000
b10 W
b10 &
b0 V
b100 <
b111 7
12
1P
1"
1#
#1140000
0"
0#
#1150000
b110 4
b110 Q
b10 J
b0 <
b110 8
b110 =
b110100000000000 $
b110100000000000 ?
b10 :
b10 A
b101 9
b101 @
0.
0B
10
1C
02
0P
1"
1#
#1160000
0"
0#
#1170000
b10 D
b10 '
b1 <
00
0C
1.
1B
1"
1#
#1180000
0"
0#
#1190000
b10 <
b100 +
1"
1#
#1200000
0"
0#
#1210000
b111 D
b111 '
b100 9
b100 @
1"
1#
#1211000
b110 O
b1000 R
b11 <
b111 5
b111 K
b111 Y
b1000 L
b110 U
b1110 S
b11 T
#1220000
0"
0#
#1230000
b110 W
b110 &
b1 O
b11 R
b0 V
b100 <
b10 5
b10 K
b10 Y
b11 L
b1 U
b100 S
b1 T
12
1P
1"
1#
#1240000
0"
0#
#1250000
b1100 4
b1100 Q
b110 I
b0 <
b111 8
b111 =
b1100000011000000 $
b1100000011000000 ?
b110 :
b110 A
0.
0B
10
1C
02
0P
1"
1#
#1260000
0"
0#
#1270000
b110 D
b110 '
b1 <
00
0C
1.
1B
1"
1#
#1280000
0"
0#
#1290000
b10 <
b11 ,
b0 +
1"
1#
#1300000
0"
0#
#1310000
b1 D
b1 '
b0 9
b0 @
1"
1#
#1311000
b0 O
b10 R
b11 9
b11 @
b1 5
b1 K
b1 Y
b10 L
b0 U
b10 S
b0 T
#1312000
b11 <
#1320000
0"
0#
#1330000
b100 <
1"
1#
#1340000
0"
0#
#1350000
b0 <
b1000 8
b1000 =
b1100011101000000 $
b1100011101000000 ?
b1 :
b1 A
b0 9
b0 @
0.
0B
10
1C
1"
1#
#1360000
0"
0#
#1370000
b1 <
00
0C
1.
1B
1"
1#
#1380000
0"
0#
#1390000
b10 <
b101 ,
b11 +
1"
1#
#1400000
0"
0#
#1410000
b11 9
b11 @
1"
1#
#1411000
b10 D
b10 '
b101 9
b101 @
#1412000
b11 <
b10 6
b10 M
b11 L
b111111111 U
b100 S
#1420000
0"
0#
#1430000
b1 O
b11 R
b100 <
b10 5
b10 K
b10 Y
b100 L
b0 U
b1000 S
1"
1#
#1440000
0"
0#
